exordium/__init__.py
exordium/audio/__init__.py
exordium/audio/clap.py
exordium/audio/io.py
exordium/audio/smile.py
exordium/audio/spectrogram.py
exordium/audio/wav2vec.py
exordium/audio/wavlm.py
exordium/text/__init__.py
exordium/text/bert.py
exordium/text/roberta.py
exordium/text/whisper.py
exordium/text/xml_roberta.py
exordium/utils/__init__.py
exordium/utils/ckpt.py
exordium/utils/concurent.py
exordium/utils/decorator.py
exordium/utils/device.py
exordium/utils/loss.py
exordium/utils/normalize.py
exordium/utils/padding.py
exordium/video/__init__.py
exordium/video/bb.py
exordium/video/blur.py
exordium/video/bodypose.py
exordium/video/clip.py
exordium/video/detection.py
exordium/video/dynimg.py
exordium/video/emonet.py
exordium/video/fabnet.py
exordium/video/facedetector.py
exordium/video/facemesh.py
exordium/video/gaze.py
exordium/video/io.py
exordium/video/io_av.py
exordium/video/io_decord.py
exordium/video/io_moviepy.py
exordium/video/io_torch.py
exordium/video/iris.py
exordium/video/l2csnet.py
exordium/video/openface.py
exordium/video/opengraphau.py
exordium/video/r2plus1d.py
exordium/video/resnet.py
exordium/video/rvm.py
exordium/video/swin_transformers.py
exordium/video/tddfa_v2.py
exordium/video/tracker.py
exordium/video/transform.py
exordium/visualization/gaze.py
exordium/visualization/graph.py
exordium/visualization/headpose.py
exordium/visualization/landmarks.py
exordium/visualization/landmarks_detection.py
exordium/visualization/saliency.py
exordium/visualization/table.py
exordium-1.4.2.dist-info/METADATA
exordium-1.4.2.dist-info/WHEEL
exordium-1.4.2.dist-info/licenses/LICENSE
exordium-1.4.2.dist-info/RECORD
