Metadata-Version: 2.4
Name: exordium
Version: 1.4.2
Summary: Collection of utility tools and deep learning methods.
Project-URL: Documentation, https://github.com/fodorad/exordium#readme
Project-URL: Issues, https://github.com/fodorad/exordium/issues
Project-URL: Source, https://github.com/fodorad/exordium
Author-email: fodorad <foauaai@inf.elte.hu>
License-Expression: MIT
License-File: LICENSE
Keywords: audio,detection,multimodal,preprocess,text,tracking,video
Classifier: License :: OSI Approved :: MIT License
Classifier: Operating System :: OS Independent
Classifier: Programming Language :: Python :: 3
Requires-Python: >=3.11
Requires-Dist: matplotlib
Requires-Dist: opencv-contrib-python
Requires-Dist: opencv-python
Requires-Dist: pillow
Requires-Dist: scipy
Requires-Dist: toml
Requires-Dist: torch
Requires-Dist: tqdm
Provides-Extra: all
Requires-Dist: accelerate; extra == 'all'
Requires-Dist: av; extra == 'all'
Requires-Dist: batch-face; extra == 'all'
Requires-Dist: decord; extra == 'all'
Requires-Dist: deepface; extra == 'all'
Requires-Dist: einops; extra == 'all'
Requires-Dist: librosa; extra == 'all'
Requires-Dist: mediapipe; extra == 'all'
Requires-Dist: moviepy; extra == 'all'
Requires-Dist: msclap; extra == 'all'
Requires-Dist: onnx; extra == 'all'
Requires-Dist: onnxruntime; extra == 'all'
Requires-Dist: open-clip-torch; extra == 'all'
Requires-Dist: opensmile; extra == 'all'
Requires-Dist: optimum; extra == 'all'
Requires-Dist: pandas; extra == 'all'
Requires-Dist: tensorflow; extra == 'all'
Requires-Dist: tf-keras==2.16.0; extra == 'all'
Requires-Dist: timm; extra == 'all'
Requires-Dist: torchaudio; extra == 'all'
Requires-Dist: torchvision; extra == 'all'
Requires-Dist: transformers; extra == 'all'
Requires-Dist: types-pyyaml; extra == 'all'
Provides-Extra: audio
Requires-Dist: librosa; extra == 'audio'
Requires-Dist: msclap; extra == 'audio'
Requires-Dist: opensmile; extra == 'audio'
Requires-Dist: tf-keras==2.16.0; extra == 'audio'
Requires-Dist: torchaudio; extra == 'audio'
Requires-Dist: transformers; extra == 'audio'
Provides-Extra: detection
Requires-Dist: batch-face; extra == 'detection'
Requires-Dist: deepface; extra == 'detection'
Requires-Dist: tensorflow; extra == 'detection'
Requires-Dist: torchvision; extra == 'detection'
Provides-Extra: tddfa
Requires-Dist: onnx; extra == 'tddfa'
Requires-Dist: onnxruntime; extra == 'tddfa'
Requires-Dist: types-pyyaml; extra == 'tddfa'
Provides-Extra: text
Requires-Dist: accelerate; extra == 'text'
Requires-Dist: optimum; extra == 'text'
Requires-Dist: transformers; extra == 'text'
Provides-Extra: video
Requires-Dist: av; extra == 'video'
Requires-Dist: decord; extra == 'video'
Requires-Dist: einops; extra == 'video'
Requires-Dist: mediapipe; extra == 'video'
Requires-Dist: moviepy; extra == 'video'
Requires-Dist: open-clip-torch; extra == 'video'
Requires-Dist: pandas; extra == 'video'
Requires-Dist: timm; extra == 'video'
